kryptograpi/__init__.py
kryptograpi/functions.py
kryptograpi-0.5.dist-info/LICENSE
kryptograpi-0.5.dist-info/METADATA
kryptograpi-0.5.dist-info/WHEEL
kryptograpi-0.5.dist-info/top_level.txt
kryptograpi-0.5.dist-info/RECORD
