Metadata-Version: 2.1
Name: kryptograpi
Version: 0.5
Summary: A library using mpmath and requests
Home-page: https://github.com/swupel/kryptograpi
Author: Anton Graller
Author-email: anton.graller@swupelpms.com
License: MIT
Classifier: Programming Language :: Python :: 3
Classifier: License :: OSI Approved :: MIT License
Classifier: Operating System :: OS Independent
Requires-Python: >=3.6
License-File: LICENSE
